LICENSE
README.md
pyproject.toml
setup.py
./LambertProblem/__init__.py
LambertProblem.egg-info/PKG-INFO
LambertProblem.egg-info/SOURCES.txt
LambertProblem.egg-info/dependency_links.txt
LambertProblem.egg-info/entry_points.txt
LambertProblem.egg-info/requires.txt
LambertProblem.egg-info/top_level.txt