Metadata-Version: 2.1
Name: LambertProblem
Version: 0.7
Summary: Solve the lambert problem for orbital mechanics
Home-page: https://pypi.org/project/LambertProblem
Author: juaniuwu
Author-email: juanita.agudelo@udea.edu.co
License: MIT
Keywords: Lambert equation orbital mechanics solve
Platform: UNKNOWN
Classifier: Programming Language :: Python :: 3
Classifier: License :: OSI Approved :: MIT License
Classifier: Operating System :: OS Independent
License-File: LICENSE
